[{"localID":441,"teamName":"Boomers","firstName":"Hank","lastName":"Aaron","primaryPosition":9,"pitcherRole":null,"power":99,"contact":98,"speed":35,"fielding":73,"arm":87,"velocity":null,"junk":null,"accuracy":null,"age":36,"trait":0,"subType":1},
{"localID":441,"teamName":"Boomers","firstName":"Hank","lastName":"Aaron","primaryPosition":9,"pitcherRole":null,"power":99,"contact":98,"speed":35,"fielding":73,"arm":87,"velocity":null,"junk":null,"accuracy":null,"age":36,"trait":3,"subType":4},
{"localID":443,"teamName":"Joyriders","firstName":"Rick","lastName":"Aguilera","primaryPosition":1,"pitcherRole":2,"power":17,"contact":6,"speed":13,"fielding":77,"arm":null,"velocity":35,"junk":33,"accuracy":55,"age":38,"trait":null,"subType":null},
{"localID":444,"teamName":"Boomers","firstName":"Dick","lastName":"Allen","primaryPosition":3,"pitcherRole":null,"power":91,"contact":70,"speed":45,"fielding":40,"arm":46,"velocity":null,"junk":null,"accuracy":null,"age":20,"trait":0,"subType":0},
{"localID":444,"teamName":"Boomers","firstName":"Dick","lastName":"Allen","primaryPosition":3,"pitcherRole":null,"power":91,"contact":70,"speed":45,"fielding":40,"arm":46,"velocity":null,"junk":null,"accuracy":null,"age":20,"trait":38,"subType":6},
{"localID":445,"teamName":"Spirit","firstName":"Brady","lastName":"Anderson","primaryPosition":9,"pitcherRole":null,"power":55,"contact":46,"speed":91,"fielding":69,"arm":18,"velocity":null,"junk":null,"accuracy":null,"age":19,"trait":8,"subType":6},
{"localID":446,"teamName":"Mammotanks","firstName":"Rick","lastName":"Ankiel","primaryPosition":1,"pitcherRole":1,"power":65,"contact":5,"speed":57,"fielding":42,"arm":null,"velocity":90,"junk":5,"accuracy":3,"age":20,"trait":24,"subType":22},
{"localID":446,"teamName":"Mammotanks","firstName":"Rick","lastName":"Ankiel","primaryPosition":1,"pitcherRole":1,"power":65,"contact":5,"speed":57,"fielding":42,"arm":null,"velocity":90,"junk":5,"accuracy":3,"age":20,"trait":31,"subType":7},
{"localID":447,"teamName":"Mammotanks","firstName":"Bronson","lastName":"Arroyo","primaryPosition":1,"pitcherRole":1,"power":15,"contact":7,"speed":25,"fielding":79,"arm":null,"velocity":37,"junk":48,"accuracy":75,"age":33,"trait":19,"subType":7},
{"localID":451,"teamName":"Joyriders","firstName":"Paul","lastName":"Assenmacher","primaryPosition":1,"pitcherRole":3,"power":2,"contact":0,"speed":19,"fielding":71,"arm":null,"velocity":52,"junk":59,"accuracy":54,"age":27,"trait":19,"subType":7},
{"localID":452,"teamName":"Empire","firstName":"Rich","lastName":"Aurilia","primaryPosition":6,"pitcherRole":null,"power":48,"contact":54,"speed":46,"fielding":44,"arm":73,"velocity":null,"junk":null,"accuracy":null,"age":34,"trait":9,"subType":6},
{"localID":454,"teamName":"Empire","firstName":"Jeff","lastName":"Bagwell","primaryPosition":3,"pitcherRole":null,"power":95,"contact":79,"speed":82,"fielding":61,"arm":25,"velocity":null,"junk":null,"accuracy":null,"age":28,"trait":3,"subType":3},
{"localID":454,"teamName":"Empire","firstName":"Jeff","lastName":"Bagwell","primaryPosition":3,"pitcherRole":null,"power":95,"contact":79,"speed":82,"fielding":61,"arm":25,"velocity":null,"junk":null,"accuracy":null,"age":28,"trait":12,"subType":10},
{"localID":455,"teamName":"Empire","firstName":"Grant","lastName":"Balfour","primaryPosition":1,"pitcherRole":3,"power":2,"contact":4,"speed":5,"fielding":59,"arm":null,"velocity":70,"junk":34,"accuracy":26,"age":30,"trait":6,"subType":7},
{"localID":455,"teamName":"Empire","firstName":"Grant","lastName":"Balfour","primaryPosition":1,"pitcherRole":3,"power":2,"contact":4,"speed":5,"fielding":59,"arm":null,"velocity":70,"junk":34,"accuracy":26,"age":30,"trait":39,"subType":7},
{"localID":458,"teamName":"Originators","firstName":"Ernie","lastName":"Banks","primaryPosition":3,"pitcherRole":null,"power":86,"contact":80,"speed":25,"fielding":95,"arm":22,"velocity":null,"junk":null,"accuracy":null,"age":34,"trait":0,"subType":0},
{"localID":458,"teamName":"Originators","firstName":"Ernie","lastName":"Banks","primaryPosition":3,"pitcherRole":null,"power":86,"contact":80,"speed":25,"fielding":95,"arm":22,"velocity":null,"junk":null,"accuracy":null,"age":34,"trait":29,"subType":6},
{"localID":459,"teamName":"Thrillers","firstName":"Jesse","lastName":"Barfield","primaryPosition":9,"pitcherRole":null,"power":77,"contact":24,"speed":68,"fielding":57,"arm":99,"velocity":null,"junk":null,"accuracy":null,"age":29,"trait":null,"subType":null},
{"localID":464,"teamName":"Thrillers","firstName":"Steve","lastName":"Bedrosian","primaryPosition":1,"pitcherRole":3,"power":0,"contact":6,"speed":4,"fielding":40,"arm":null,"velocity":88,"junk":71,"accuracy":42,"age":27,"trait":21,"subType":7},
{"localID":467,"teamName":"Boomers","firstName":"Vida","lastName":"Blue","primaryPosition":1,"pitcherRole":1,"power":13,"contact":7,"speed":12,"fielding":57,"arm":null,"velocity":80,"junk":59,"accuracy":62,"age":28,"trait":19,"subType":6},
{"localID":467,"teamName":"Boomers","firstName":"Vida","lastName":"Blue","primaryPosition":1,"pitcherRole":1,"power":13,"contact":7,"speed":12,"fielding":57,"arm":null,"velocity":80,"junk":59,"accuracy":62,"age":28,"trait":21,"subType":7},
{"localID":469,"teamName":"Spirit","firstName":"Chad","lastName":"Bradford","primaryPosition":1,"pitcherRole":3,"power":7,"contact":0,"speed":0,"fielding":85,"arm":null,"velocity":2,"junk":72,"accuracy":50,"age":32,"trait":21,"subType":7},
{"localID":470,"teamName":"Mammotanks","firstName":"Ryan","lastName":"Braun","primaryPosition":7,"pitcherRole":null,"power":96,"contact":62,"speed":51,"fielding":37,"arm":54,"velocity":null,"junk":null,"accuracy":null,"age":29,"trait":0,"subType":1},
{"localID":471,"teamName":"Joyriders","firstName":"George","lastName":"Brett","primaryPosition":5,"pitcherRole":null,"power":64,"contact":91,"speed":79,"fielding":70,"arm":62,"velocity":null,"junk":null,"accuracy":null,"age":33,"trait":1,"subType":0},
{"localID":471,"teamName":"Joyriders","firstName":"George","lastName":"Brett","primaryPosition":5,"pitcherRole":null,"power":64,"contact":91,"speed":79,"fielding":70,"arm":62,"velocity":null,"junk":null,"accuracy":null,"age":33,"trait":2,"subType":6},
{"localID":474,"teamName":"Joyriders","firstName":"Brett","lastName":"Butler","primaryPosition":8,"pitcherRole":null,"power":21,"contact":82,"speed":96,"fielding":96,"arm":40,"velocity":null,"junk":null,"accuracy":null,"age":37,"trait":17,"subType":7},
{"localID":474,"teamName":"Joyriders","firstName":"Brett","lastName":"Butler","primaryPosition":8,"pitcherRole":null,"power":21,"contact":82,"speed":96,"fielding":96,"arm":40,"velocity":null,"junk":null,"accuracy":null,"age":37,"trait":28,"subType":6},
{"localID":477,"teamName":"Empire","firstName":"Orlando","lastName":"Cabrera","primaryPosition":6,"pitcherRole":null,"power":29,"contact":67,"speed":72,"fielding":67,"arm":78,"velocity":null,"junk":null,"accuracy":null,"age":23,"trait":1,"subType":1},
{"localID":477,"teamName":"Empire","firstName":"Orlando","lastName":"Cabrera","primaryPosition":6,"pitcherRole":null,"power":29,"contact":67,"speed":72,"fielding":67,"arm":78,"velocity":null,"junk":null,"accuracy":null,"age":23,"trait":17,"subType":7},
{"localID":478,"teamName":"Empire","firstName":"Matt","lastName":"Cain","primaryPosition":1,"pitcherRole":1,"power":9,"contact":7,"speed":12,"fielding":42,"arm":null,"velocity":56,"junk":39,"accuracy":49,"age":33,"trait":19,"subType":6},
{"localID":479,"teamName":"Rakers","firstName":"Mike","lastName":"Cameron","primaryPosition":8,"pitcherRole":null,"power":73,"contact":24,"speed":94,"fielding":96,"arm":47,"velocity":null,"junk":null,"accuracy":null,"age":37,"trait":37,"subType":6},
{"localID":481,"teamName":"Thrillers","firstName":"Gary","lastName":"Carter","primaryPosition":2,"pitcherRole":null,"power":68,"contact":66,"speed":52,"fielding":97,"arm":79,"velocity":null,"junk":null,"accuracy":null,"age":34,"trait":9,"subType":6},
{"localID":481,"teamName":"Thrillers","firstName":"Gary","lastName":"Carter","primaryPosition":2,"pitcherRole":null,"power":68,"contact":66,"speed":52,"fielding":97,"arm":79,"velocity":null,"junk":null,"accuracy":null,"age":34,"trait":16,"subType":6},
{"localID":482,"teamName":"Originators","firstName":"Orlando","lastName":"Cepeda","primaryPosition":7,"pitcherRole":null,"power":77,"contact":76,"speed":24,"fielding":54,"arm":87,"velocity":null,"junk":null,"accuracy":null,"age":28,"trait":13,"subType":6},
{"localID":488,"teamName":"Spirit","firstName":"Will","lastName":"Clark","primaryPosition":3,"pitcherRole":null,"power":66,"contact":76,"speed":65,"fielding":66,"arm":10,"velocity":null,"junk":null,"accuracy":null,"age":20,"trait":4,"subType":6},
{"localID":488,"teamName":"Spirit","firstName":"Will","lastName":"Clark","primaryPosition":3,"pitcherRole":null,"power":66,"contact":76,"speed":65,"fielding":66,"arm":10,"velocity":null,"junk":null,"accuracy":null,"age":20,"trait":33,"subType":26},
{"localID":489,"teamName":"Thrillers","firstName":"Jack","lastName":"Clark","primaryPosition":9,"pitcherRole":null,"power":86,"contact":57,"speed":68,"fielding":64,"arm":93,"velocity":null,"junk":null,"accuracy":null,"age":38,"trait":32,"subType":7},
{"localID":489,"teamName":"Thrillers","firstName":"Jack","lastName":"Clark","primaryPosition":9,"pitcherRole":null,"power":86,"contact":57,"speed":68,"fielding":64,"arm":93,"velocity":null,"junk":null,"accuracy":null,"age":38,"trait":36,"subType":6},
{"localID":490,"teamName":"Spirit","firstName":"Royce","lastName":"Clayton","primaryPosition":6,"pitcherRole":null,"power":27,"contact":36,"speed":77,"fielding":64,"arm":87,"velocity":null,"junk":null,"accuracy":null,"age":27,"trait":40,"subType":6},
{"localID":496,"teamName":"Boomers","firstName":"Cecil","lastName":"Cooper","primaryPosition":3,"pitcherRole":null,"power":52,"contact":76,"speed":60,"fielding":57,"arm":6,"velocity":null,"junk":null,"accuracy":null,"age":29,"trait":1,"subType":0},
{"localID":497,"teamName":"Mammotanks","firstName":"Carl","lastName":"Crawford","primaryPosition":7,"pitcherRole":null,"power":46,"contact":66,"speed":89,"fielding":59,"arm":63,"velocity":null,"junk":null,"accuracy":null,"age":33,"trait":8,"subType":6},
{"localID":500,"teamName":"Joyriders","firstName":"Chili","lastName":"Davis","primaryPosition":8,"pitcherRole":null,"power":63,"contact":51,"speed":63,"fielding":46,"arm":58,"velocity":null,"junk":null,"accuracy":null,"age":27,"trait":null,"subType":null},
{"localID":503,"teamName":"Thrillers","firstName":"Andre","lastName":"Dawson","primaryPosition":8,"pitcherRole":null,"power":72,"contact":62,"speed":83,"fielding":69,"arm":60,"velocity":null,"junk":null,"accuracy":null,"age":39,"trait":0,"subType":1},
{"localID":506,"teamName":"Rakers","firstName":"Carlos","lastName":"Delgado","primaryPosition":3,"pitcherRole":null,"power":96,"contact":48,"speed":50,"fielding":53,"arm":11,"velocity":null,"junk":null,"accuracy":null,"age":27,"trait":null,"subType":null},
{"localID":508,"teamName":"Mammotanks","firstName":"Ray","lastName":"Durham","primaryPosition":4,"pitcherRole":null,"power":47,"contact":58,"speed":86,"fielding":32,"arm":45,"velocity":null,"junk":null,"accuracy":null,"age":35,"trait":null,"subType":null},
{"localID":511,"teamName":"Spirit","firstName":"Jim","lastName":"Edmonds","primaryPosition":8,"pitcherRole":null,"power":86,"contact":43,"speed":61,"fielding":92,"arm":87,"velocity":null,"junk":null,"accuracy":null,"age":21,"trait":17,"subType":7},
{"localID":511,"teamName":"Spirit","firstName":"Jim","lastName":"Edmonds","primaryPosition":8,"pitcherRole":null,"power":86,"contact":43,"speed":61,"fielding":92,"arm":87,"velocity":null,"junk":null,"accuracy":null,"age":21,"trait":37,"subType":6},
{"localID":512,"teamName":"Joyriders","firstName":"Dwight","lastName":"Evans","primaryPosition":9,"pitcherRole":null,"power":84,"contact":69,"speed":79,"fielding":68,"arm":91,"velocity":null,"junk":null,"accuracy":null,"age":34,"trait":null,"subType":null},
{"localID":515,"teamName":"Rakers","firstName":"Jeff","lastName":"Fassero","primaryPosition":1,"pitcherRole":2,"power":2,"contact":0,"speed":55,"fielding":74,"arm":null,"velocity":49,"junk":39,"accuracy":58,"age":22,"trait":18,"subType":6},
{"localID":516,"teamName":"Originators","firstName":"Bob","lastName":"Feller","primaryPosition":1,"pitcherRole":1,"power":15,"contact":5,"speed":5,"fielding":50,"arm":null,"velocity":90,"junk":74,"accuracy":43,"age":18,"trait":32,"subType":6},
{"localID":518,"teamName":"Originators","firstName":"Rollie","lastName":"Fingers","primaryPosition":1,"pitcherRole":4,"power":11,"contact":6,"speed":1,"fielding":77,"arm":null,"velocity":69,"junk":77,"accuracy":83,"age":33,"trait":20,"subType":6},
{"localID":519,"teamName":"Joyriders","firstName":"John","lastName":"Franco","primaryPosition":1,"pitcherRole":3,"power":0,"contact":4,"speed":27,"fielding":78,"arm":null,"velocity":62,"junk":81,"accuracy":60,"age":33,"trait":32,"subType":6},
{"localID":522,"teamName":"Rakers","firstName":"Eric","lastName":"Gagne","primaryPosition":1,"pitcherRole":4,"power":6,"contact":4,"speed":19,"fielding":44,"arm":null,"velocity":80,"junk":45,"accuracy":24,"age":22,"trait":7,"subType":6},
{"localID":523,"teamName":"Joyriders","firstName":"Ron","lastName":"Gant","primaryPosition":7,"pitcherRole":null,"power":77,"contact":34,"speed":87,"fielding":39,"arm":38,"velocity":null,"junk":null,"accuracy":null,"age":21,"trait":27,"subType":6},
{"localID":524,"teamName":"Originators","firstName":"Steve","lastName":"Garvey","primaryPosition":3,"pitcherRole":null,"power":53,"contact":81,"speed":53,"fielding":64,"arm":9,"velocity":null,"junk":null,"accuracy":null,"age":22,"trait":2,"subType":7},
{"localID":526,"teamName":"Empire","firstName":"Jason","lastName":"Giambi","primaryPosition":3,"pitcherRole":null,"power":91,"contact":54,"speed":49,"fielding":47,"arm":10,"velocity":null,"junk":null,"accuracy":null,"age":24,"trait":26,"subType":7},
{"localID":526,"teamName":"Empire","firstName":"Jason","lastName":"Giambi","primaryPosition":3,"pitcherRole":null,"power":91,"contact":54,"speed":49,"fielding":47,"arm":10,"velocity":null,"junk":null,"accuracy":null,"age":24,"trait":35,"subType":6},
{"localID":529,"teamName":"Thrillers","firstName":"Kirk","lastName":"Gibson","primaryPosition":7,"pitcherRole":null,"power":69,"contact":41,"speed":92,"fielding":36,"arm":18,"velocity":null,"junk":null,"accuracy":null,"age":23,"trait":0,"subType":0},
{"localID":529,"teamName":"Thrillers","firstName":"Kirk","lastName":"Gibson","primaryPosition":7,"pitcherRole":null,"power":69,"contact":41,"speed":92,"fielding":36,"arm":18,"velocity":null,"junk":null,"accuracy":null,"age":23,"trait":15,"subType":6},
{"localID":530,"teamName":"Joyriders","firstName":"Tom","lastName":"Glavine","primaryPosition":1,"pitcherRole":1,"power":7,"contact":0,"speed":19,"fielding":90,"arm":null,"velocity":54,"junk":75,"accuracy":73,"age":19,"trait":22,"subType":19},
{"localID":534,"teamName":"Thrillers","firstName":"Goose","lastName":"Gossage","primaryPosition":1,"pitcherRole":4,"power":6,"contact":3,"speed":3,"fielding":35,"arm":null,"velocity":97,"junk":86,"accuracy":60,"age":35,"trait":20,"subType":6},
{"localID":534,"teamName":"Thrillers","firstName":"Goose","lastName":"Gossage","primaryPosition":1,"pitcherRole":4,"power":6,"contact":3,"speed":3,"fielding":35,"arm":null,"velocity":97,"junk":86,"accuracy":60,"age":35,"trait":22,"subType":15},
{"localID":535,"teamName":"Joyriders","firstName":"Mark","lastName":"Grace","primaryPosition":3,"pitcherRole":null,"power":42,"contact":93,"speed":60,"fielding":68,"arm":10,"velocity":null,"junk":null,"accuracy":null,"age":21,"trait":12,"subType":11},
{"localID":537,"teamName":"Mammotanks","firstName":"Vladimir","lastName":"Guerrero","primaryPosition":9,"pitcherRole":null,"power":83,"contact":87,"speed":62,"fielding":12,"arm":75,"velocity":null,"junk":null,"accuracy":null,"age":23,"trait":11,"subType":6},
{"localID":537,"teamName":"Mammotanks","firstName":"Vladimir","lastName":"Guerrero","primaryPosition":9,"pitcherRole":null,"power":83,"contact":87,"speed":62,"fielding":12,"arm":75,"velocity":null,"junk":null,"accuracy":null,"age":23,"trait":36,"subType":6},
{"localID":539,"teamName":"Thrillers","firstName":"Ron","lastName":"Guidry","primaryPosition":1,"pitcherRole":2,"power":4,"contact":7,"speed":0,"fielding":68,"arm":null,"velocity":88,"junk":24,"accuracy":84,"age":23,"trait":18,"subType":6},
{"localID":543,"teamName":"Originators","firstName":"Dick","lastName":"Hall","primaryPosition":1,"pitcherRole":2,"power":13,"contact":14,"speed":15,"fielding":45,"arm":null,"velocity":33,"junk":24,"accuracy":82,"age":34,"trait":24,"subType":22},
{"localID":548,"teamName":"Thrillers","firstName":"Tom","lastName":"Henke","primaryPosition":1,"pitcherRole":3,"power":5,"contact":6,"speed":3,"fielding":64,"arm":null,"velocity":63,"junk":96,"accuracy":68,"age":38,"trait":19,"subType":7},
{"localID":549,"teamName":"Spirit","firstName":"Pat","lastName":"Hentgen","primaryPosition":1,"pitcherRole":1,"power":0,"contact":0,"speed":14,"fielding":61,"arm":null,"velocity":44,"junk":58,"accuracy":58,"age":28,"trait":25,"subType":6},
{"localID":550,"teamName":"Spirit","firstName":"Roberto","lastName":"Hernandez","primaryPosition":1,"pitcherRole":4,"power":6,"contact":2,"speed":2,"fielding":31,"arm":null,"velocity":92,"junk":66,"accuracy":48,"age":27,"trait":null,"subType":null},
{"localID":551,"teamName":"Thrillers","firstName":"Keith","lastName":"Hernandez","primaryPosition":3,"pitcherRole":null,"power":49,"contact":85,"speed":69,"fielding":74,"arm":18,"velocity":null,"junk":null,"accuracy":null,"age":32,"trait":1,"subType":0},
{"localID":552,"teamName":"Boomers","firstName":"Tom","lastName":"Herr","primaryPosition":4,"pitcherRole":null,"power":15,"contact":67,"speed":76,"fielding":67,"arm":43,"velocity":null,"junk":null,"accuracy":null,"age":39,"trait":null,"subType":null},
{"localID":554,"teamName":"Thrillers","firstName":"Al","lastName":"Holland","primaryPosition":1,"pitcherRole":3,"power":1,"contact":2,"speed":22,"fielding":2,"arm":null,"velocity":33,"junk":63,"accuracy":47,"age":34,"trait":null,"subType":null},
{"localID":556,"teamName":"Rakers","firstName":"Orlando","lastName":"Hudson","primaryPosition":4,"pitcherRole":null,"power":36,"contact":51,"speed":75,"fielding":82,"arm":50,"velocity":null,"junk":null,"accuracy":null,"age":39,"trait":26,"subType":6},
{"localID":557,"teamName":"Mammotanks","firstName":"Torii","lastName":"Hunter","primaryPosition":8,"pitcherRole":null,"power":66,"contact":47,"speed":65,"fielding":78,"arm":65,"velocity":null,"junk":null,"accuracy":null,"age":23,"trait":29,"subType":6},
{"localID":560,"teamName":"Spirit","firstName":"Mike","lastName":"Jackson","primaryPosition":1,"pitcherRole":3,"power":2,"contact":7,"speed":0,"fielding":58,"arm":null,"velocity":86,"junk":75,"accuracy":40,"age":20,"trait":5,"subType":13},
{"localID":560,"teamName":"Spirit","firstName":"Mike","lastName":"Jackson","primaryPosition":1,"pitcherRole":3,"power":2,"contact":7,"speed":0,"fielding":58,"arm":null,"velocity":86,"junk":75,"accuracy":40,"age":20,"trait":6,"subType":7},
{"localID":561,"teamName":"Boomers","firstName":"Tommy","lastName":"John","primaryPosition":1,"pitcherRole":2,"power":9,"contact":5,"speed":5,"fielding":94,"arm":null,"velocity":62,"junk":58,"accuracy":90,"age":26,"trait":6,"subType":6},
{"localID":561,"teamName":"Boomers","firstName":"Tommy","lastName":"John","primaryPosition":1,"pitcherRole":2,"power":9,"contact":5,"speed":5,"fielding":94,"arm":null,"velocity":62,"junk":58,"accuracy":90,"age":26,"trait":34,"subType":7},
{"localID":564,"teamName":"Spirit","firstName":"Randy","lastName":"Johnson","primaryPosition":1,"pitcherRole":1,"power":7,"contact":1,"speed":7,"fielding":11,"arm":null,"velocity":98,"junk":86,"accuracy":74,"age":23,"trait":7,"subType":6},
{"localID":564,"teamName":"Spirit","firstName":"Randy","lastName":"Johnson","primaryPosition":1,"pitcherRole":1,"power":7,"contact":1,"speed":7,"fielding":11,"arm":null,"velocity":98,"junk":86,"accuracy":74,"age":23,"trait":22,"subType":18},
{"localID":565,"teamName":"Empire","firstName":"Andruw","lastName":"Jones","primaryPosition":8,"pitcherRole":null,"power":87,"contact":33,"speed":75,"fielding":98,"arm":81,"velocity":null,"junk":null,"accuracy":null,"age":32,"trait":37,"subType":6},
{"localID":568,"teamName":"Rakers","firstName":"Jason","lastName":"Kendall","primaryPosition":2,"pitcherRole":null,"power":24,"contact":84,"speed":71,"fielding":87,"arm":79,"velocity":null,"junk":null,"accuracy":null,"age":34,"trait":34,"subType":7},
{"localID":569,"teamName":"Joyriders","firstName":"Chuck","lastName":"Knoblauch","primaryPosition":4,"pitcherRole":null,"power":33,"contact":80,"speed":95,"fielding":34,"arm":59,"velocity":null,"junk":null,"accuracy":null,"age":20,"trait":13,"subType":6},
{"localID":569,"teamName":"Joyriders","firstName":"Chuck","lastName":"Knoblauch","primaryPosition":4,"pitcherRole":null,"power":33,"contact":80,"speed":95,"fielding":34,"arm":59,"velocity":null,"junk":null,"accuracy":null,"age":20,"trait":30,"subType":7},
{"localID":570,"teamName":"Spirit","firstName":"Paul","lastName":"Konerko","primaryPosition":3,"pitcherRole":null,"power":78,"contact":61,"speed":40,"fielding":62,"arm":11,"velocity":null,"junk":null,"accuracy":null,"age":21,"trait":0,"subType":1},
{"localID":571,"teamName":"Thrillers","firstName":"John","lastName":"Kruk","primaryPosition":7,"pitcherRole":null,"power":36,"contact":61,"speed":60,"fielding":50,"arm":65,"velocity":null,"junk":null,"accuracy":null,"age":21,"trait":10,"subType":8},
{"localID":571,"teamName":"Thrillers","firstName":"John","lastName":"Kruk","primaryPosition":7,"pitcherRole":null,"power":36,"contact":61,"speed":60,"fielding":50,"arm":65,"velocity":null,"junk":null,"accuracy":null,"age":21,"trait":26,"subType":7},
{"localID":572,"teamName":"Thrillers","firstName":"Mike","lastName":"Krukow","primaryPosition":1,"pitcherRole":1,"power":14,"contact":1,"speed":24,"fielding":46,"arm":null,"velocity":53,"junk":32,"accuracy":55,"age":29,"trait":6,"subType":7},
{"localID":574,"teamName":"Boomers","firstName":"Carney","lastName":"Lansford","primaryPosition":5,"pitcherRole":null,"power":39,"contact":83,"speed":77,"fielding":52,"arm":75,"velocity":null,"junk":null,"accuracy":null,"age":21,"trait":3,"subType":4},
{"localID":577,"teamName":"Mammotanks","firstName":"Barry","lastName":"Larkin","primaryPosition":6,"pitcherRole":null,"power":47,"contact":85,"speed":91,"fielding":74,"arm":87,"velocity":null,"junk":null,"accuracy":null,"age":36,"trait":29,"subType":6},
{"localID":582,"teamName":"Boomers","firstName":"Frank","lastName":"Linzy","primaryPosition":1,"pitcherRole":3,"power":2,"contact":2,"speed":7,"fielding":97,"arm":null,"velocity":52,"junk":48,"accuracy":61,"age":27,"trait":18,"subType":7},
{"localID":582,"teamName":"Boomers","firstName":"Frank","lastName":"Linzy","primaryPosition":1,"pitcherRole":3,"power":2,"contact":2,"speed":7,"fielding":97,"arm":null,"velocity":52,"junk":48,"accuracy":61,"age":27,"trait":33,"subType":25},
{"localID":585,"teamName":"Joyriders","firstName":"Javy","lastName":"Lopez","primaryPosition":2,"pitcherRole":null,"power":76,"contact":59,"speed":44,"fielding":52,"arm":64,"velocity":null,"junk":null,"accuracy":null,"age":36,"trait":1,"subType":1},
{"localID":585,"teamName":"Joyriders","firstName":"Javy","lastName":"Lopez","primaryPosition":2,"pitcherRole":null,"power":76,"contact":59,"speed":44,"fielding":52,"arm":64,"velocity":null,"junk":null,"accuracy":null,"age":36,"trait":34,"subType":7},
{"localID":586,"teamName":"Mammotanks","firstName":"Mark","lastName":"Loretta","primaryPosition":6,"pitcherRole":null,"power":21,"contact":76,"speed":50,"fielding":62,"arm":58,"velocity":null,"junk":null,"accuracy":null,"age":23,"trait":27,"subType":7},
{"localID":587,"teamName":"Empire","firstName":"Derek","lastName":"Lowe","primaryPosition":1,"pitcherRole":2,"power":7,"contact":3,"speed":22,"fielding":86,"arm":null,"velocity":38,"junk":65,"accuracy":70,"age":28,"trait":6,"subType":6},
{"localID":590,"teamName":"Joyriders","firstName":"Tino","lastName":"Martinez","primaryPosition":3,"pitcherRole":null,"power":73,"contact":60,"speed":49,"fielding":53,"arm":9,"velocity":null,"junk":null,"accuracy":null,"age":36,"trait":14,"subType":6},
{"localID":590,"teamName":"Joyriders","firstName":"Tino","lastName":"Martinez","primaryPosition":3,"pitcherRole":null,"power":73,"contact":60,"speed":49,"fielding":53,"arm":9,"velocity":null,"junk":null,"accuracy":null,"age":36,"trait":26,"subType":7},
{"localID":591,"teamName":"Joyriders","firstName":"Edgar","lastName":"Martinez","primaryPosition":5,"pitcherRole":null,"power":76,"contact":89,"speed":60,"fielding":38,"arm":90,"velocity":null,"junk":null,"accuracy":null,"age":26,"trait":2,"subType":6},
{"localID":592,"teamName":"Joyriders","firstName":"Dennis","lastName":"Martinez","primaryPosition":1,"pitcherRole":1,"power":3,"contact":1,"speed":22,"fielding":81,"arm":null,"velocity":51,"junk":52,"accuracy":79,"age":39,"trait":19,"subType":6},
{"localID":593,"teamName":"Originators","firstName":"Tippy","lastName":"Martinez","primaryPosition":1,"pitcherRole":3,"power":2,"contact":3,"speed":3,"fielding":58,"arm":null,"velocity":32,"junk":78,"accuracy":9,"age":36,"trait":18,"subType":6},
{"localID":596,"teamName":"Mammotanks","firstName":"Joe","lastName":"Mauer","primaryPosition":2,"pitcherRole":null,"power":62,"contact":84,"speed":36,"fielding":67,"arm":93,"velocity":null,"junk":null,"accuracy":null,"age":22,"trait":33,"subType":25},
{"localID":599,"teamName":"Mammotanks","firstName":"Fred","lastName":"McGriff","primaryPosition":3,"pitcherRole":null,"power":89,"contact":58,"speed":59,"fielding":56,"arm":15,"velocity":null,"junk":null,"accuracy":null,"age":24,"trait":0,"subType":0},
{"localID":603,"teamName":"Spirit","firstName":"Paul","lastName":"Molitor","primaryPosition":5,"pitcherRole":null,"power":54,"contact":92,"speed":93,"fielding":69,"arm":66,"velocity":null,"junk":null,"accuracy":null,"age":36,"trait":3,"subType":4},
{"localID":603,"teamName":"Spirit","firstName":"Paul","lastName":"Molitor","primaryPosition":5,"pitcherRole":null,"power":54,"contact":92,"speed":93,"fielding":69,"arm":66,"velocity":null,"junk":null,"accuracy":null,"age":36,"trait":32,"subType":6},
{"localID":607,"teamName":"Spirit","firstName":"Jeff","lastName":"Montgomery","primaryPosition":1,"pitcherRole":3,"power":2,"contact":7,"speed":3,"fielding":78,"arm":null,"velocity":57,"junk":76,"accuracy":62,"age":24,"trait":33,"subType":25},
{"localID":610,"teamName":"Thrillers","firstName":"Jack","lastName":"Morris","primaryPosition":1,"pitcherRole":1,"power":7,"contact":0,"speed":7,"fielding":66,"arm":null,"velocity":88,"junk":46,"accuracy":52,"age":38,"trait":22,"subType":21},
{"localID":613,"teamName":"Mammotanks","firstName":"Jamie","lastName":"Moyer","primaryPosition":1,"pitcherRole":1,"power":1,"contact":0,"speed":13,"fielding":82,"arm":null,"velocity":9,"junk":80,"accuracy":78,"age":40,"trait":6,"subType":6},
{"localID":613,"teamName":"Mammotanks","firstName":"Jamie","lastName":"Moyer","primaryPosition":1,"pitcherRole":1,"power":1,"contact":0,"speed":13,"fielding":82,"arm":null,"velocity":9,"junk":80,"accuracy":78,"age":40,"trait":34,"subType":6},
{"localID":619,"teamName":"Rakers","firstName":"John","lastName":"Olerud","primaryPosition":3,"pitcherRole":null,"power":64,"contact":88,"speed":48,"fielding":56,"arm":18,"velocity":null,"junk":null,"accuracy":null,"age":30,"trait":3,"subType":5},
{"localID":622,"teamName":"Empire","firstName":"Roy","lastName":"Oswalt","primaryPosition":1,"pitcherRole":1,"power":5,"contact":4,"speed":8,"fielding":75,"arm":null,"velocity":67,"junk":52,"accuracy":82,"age":33,"trait":6,"subType":6},
{"localID":625,"teamName":"Boomers","firstName":"Tony","lastName":"Perez","primaryPosition":3,"pitcherRole":null,"power":79,"contact":68,"speed":64,"fielding":63,"arm":33,"velocity":null,"junk":null,"accuracy":null,"age":27,"trait":14,"subType":6},
{"localID":625,"teamName":"Boomers","firstName":"Tony","lastName":"Perez","primaryPosition":3,"pitcherRole":null,"power":79,"contact":68,"speed":64,"fielding":63,"arm":33,"velocity":null,"junk":null,"accuracy":null,"age":27,"trait":15,"subType":6},
{"localID":626,"teamName":"Empire","firstName":"Mike","lastName":"Piazza","primaryPosition":2,"pitcherRole":null,"power":90,"contact":77,"speed":41,"fielding":56,"arm":30,"velocity":null,"junk":null,"accuracy":null,"age":19,"trait":35,"subType":6},
{"localID":627,"teamName":"Rakers","firstName":"A.J.","lastName":"Pierzynski","primaryPosition":2,"pitcherRole":null,"power":45,"contact":70,"speed":36,"fielding":36,"arm":72,"velocity":null,"junk":null,"accuracy":null,"age":37,"trait":26,"subType":7},
{"localID":629,"teamName":"Boomers","firstName":"Boog","lastName":"Powell","primaryPosition":3,"pitcherRole":null,"power":72,"contact":51,"speed":64,"fielding":40,"arm":8,"velocity":null,"junk":null,"accuracy":null,"age":27,"trait":17,"subType":6},
{"localID":630,"teamName":"Spirit","firstName":"Brad","lastName":"Radke","primaryPosition":1,"pitcherRole":1,"power":6,"contact":7,"speed":5,"fielding":92,"arm":null,"velocity":63,"junk":14,"accuracy":98,"age":38,"trait":18,"subType":7},
{"localID":631,"teamName":"Thrillers","firstName":"Willie","lastName":"Randolph","primaryPosition":4,"pitcherRole":null,"power":35,"contact":86,"speed":89,"fielding":73,"arm":52,"velocity":null,"junk":null,"accuracy":null,"age":22,"trait":1,"subType":1},
{"localID":632,"teamName":"Boomers","firstName":"Phil","lastName":"Regan","primaryPosition":1,"pitcherRole":3,"power":4,"contact":1,"speed":3,"fielding":67,"arm":null,"velocity":49,"junk":22,"accuracy":67,"age":24,"trait":null,"subType":null},
{"localID":634,"teamName":"Boomers","firstName":"Jim","lastName":"Rice","primaryPosition":9,"pitcherRole":null,"power":73,"contact":68,"speed":57,"fielding":38,"arm":88,"velocity":null,"junk":null,"accuracy":null,"age":24,"trait":36,"subType":6},
{"localID":645,"teamName":"Joyriders","firstName":"Bret","lastName":"Saberhagen","primaryPosition":1,"pitcherRole":1,"power":3,"contact":3,"speed":18,"fielding":80,"arm":null,"velocity":80,"junk":12,"accuracy":95,"age":33,"trait":22,"subType":14},
{"localID":646,"teamName":"Empire","firstName":"Tim","lastName":"Salmon","primaryPosition":9,"pitcherRole":null,"power":82,"contact":54,"speed":62,"fielding":51,"arm":74,"velocity":null,"junk":null,"accuracy":null,"age":27,"trait":null,"subType":null},
{"localID":648,"teamName":"Spirit","firstName":"Reggie","lastName":"Sanders","primaryPosition":7,"pitcherRole":null,"power":77,"contact":30,"speed":95,"fielding":57,"arm":61,"velocity":null,"junk":null,"accuracy":null,"age":30,"trait":4,"subType":7},
{"localID":655,"teamName":"Thrillers","firstName":"Steve","lastName":"Sax","primaryPosition":4,"pitcherRole":null,"power":20,"contact":82,"speed":91,"fielding":30,"arm":40,"velocity":null,"junk":null,"accuracy":null,"age":21,"trait":15,"subType":6},
{"localID":656,"teamName":"Thrillers","firstName":"Mike","lastName":"Schmidt","primaryPosition":5,"pitcherRole":null,"power":96,"contact":54,"speed":79,"fielding":98,"arm":96,"velocity":null,"junk":null,"accuracy":null,"age":35,"trait":29,"subType":6},
{"localID":656,"teamName":"Thrillers","firstName":"Mike","lastName":"Schmidt","primaryPosition":5,"pitcherRole":null,"power":96,"contact":54,"speed":79,"fielding":98,"arm":96,"velocity":null,"junk":null,"accuracy":null,"age":35,"trait":32,"subType":6},
{"localID":657,"teamName":"Originators","firstName":"Red","lastName":"Schoendienst","primaryPosition":4,"pitcherRole":null,"power":31,"contact":96,"speed":21,"fielding":85,"arm":33,"velocity":null,"junk":null,"accuracy":null,"age":23,"trait":28,"subType":6},
{"localID":659,"teamName":"Thrillers","firstName":"Mike","lastName":"Scioscia","primaryPosition":2,"pitcherRole":null,"power":24,"contact":70,"speed":42,"fielding":55,"arm":71,"velocity":null,"junk":null,"accuracy":null,"age":22,"trait":17,"subType":6},
{"localID":659,"teamName":"Thrillers","firstName":"Mike","lastName":"Scioscia","primaryPosition":2,"pitcherRole":null,"power":24,"contact":70,"speed":42,"fielding":55,"arm":71,"velocity":null,"junk":null,"accuracy":null,"age":22,"trait":26,"subType":7},
{"localID":660,"teamName":"Mammotanks","firstName":"Kyle","lastName":"Seager","primaryPosition":5,"pitcherRole":null,"power":73,"contact":44,"speed":21,"fielding":83,"arm":97,"velocity":null,"junk":null,"accuracy":null,"age":29,"trait":1,"subType":0},
{"localID":663,"teamName":"Thrillers","firstName":"Ozzie","lastName":"Smith","primaryPosition":6,"pitcherRole":null,"power":15,"contact":79,"speed":92,"fielding":99,"arm":98,"velocity":null,"junk":null,"accuracy":null,"age":31,"trait":29,"subType":6},
{"localID":663,"teamName":"Thrillers","firstName":"Ozzie","lastName":"Smith","primaryPosition":6,"pitcherRole":null,"power":15,"contact":79,"speed":92,"fielding":99,"arm":98,"velocity":null,"junk":null,"accuracy":null,"age":31,"trait":37,"subType":6},
{"localID":665,"teamName":"Rakers","firstName":"Dave","lastName":"Stieb","primaryPosition":1,"pitcherRole":1,"power":4,"contact":0,"speed":6,"fielding":89,"arm":null,"velocity":55,"junk":78,"accuracy":57,"age":32,"trait":null,"subType":null},
{"localID":666,"teamName":"Spirit","firstName":"Terry","lastName":"Steinbach","primaryPosition":2,"pitcherRole":null,"power":51,"contact":52,"speed":52,"fielding":59,"arm":79,"velocity":null,"junk":null,"accuracy":null,"age":33,"trait":null,"subType":null},
{"localID":670,"teamName":"Originators","firstName":"Jim","lastName":"Sundberg","primaryPosition":2,"pitcherRole":null,"power":41,"contact":55,"speed":58,"fielding":62,"arm":91,"velocity":null,"junk":null,"accuracy":null,"age":37,"trait":3,"subType":5},
{"localID":670,"teamName":"Originators","firstName":"Jim","lastName":"Sundberg","primaryPosition":2,"pitcherRole":null,"power":41,"contact":55,"speed":58,"fielding":62,"arm":91,"velocity":null,"junk":null,"accuracy":null,"age":37,"trait":13,"subType":6},
{"localID":672,"teamName":"Boomers","firstName":"Bruce","lastName":"Sutter","primaryPosition":1,"pitcherRole":4,"power":1,"contact":6,"speed":22,"fielding":77,"arm":null,"velocity":45,"junk":90,"accuracy":78,"age":23,"trait":7,"subType":6},
{"localID":672,"teamName":"Boomers","firstName":"Bruce","lastName":"Sutter","primaryPosition":1,"pitcherRole":4,"power":1,"contact":6,"speed":22,"fielding":77,"arm":null,"velocity":45,"junk":90,"accuracy":78,"age":23,"trait":20,"subType":7},
{"localID":675,"teamName":"Thrillers","firstName":"Frank","lastName":"Tanana","primaryPosition":1,"pitcherRole":1,"power":6,"contact":3,"speed":48,"fielding":84,"arm":null,"velocity":88,"junk":31,"accuracy":77,"age":33,"trait":33,"subType":25},
{"localID":678,"teamName":"Boomers","firstName":"Garry","lastName":"Templeton","primaryPosition":6,"pitcherRole":null,"power":23,"contact":57,"speed":78,"fielding":55,"arm":72,"velocity":null,"junk":null,"accuracy":null,"age":35,"trait":29,"subType":7},
{"localID":679,"teamName":"Boomers","firstName":"Luis","lastName":"Tiant","primaryPosition":1,"pitcherRole":2,"power":19,"contact":2,"speed":3,"fielding":48,"arm":null,"velocity":56,"junk":72,"accuracy":79,"age":26,"trait":18,"subType":7},
{"localID":679,"teamName":"Boomers","firstName":"Luis","lastName":"Tiant","primaryPosition":1,"pitcherRole":2,"power":19,"contact":2,"speed":3,"fielding":48,"arm":null,"velocity":56,"junk":72,"accuracy":79,"age":26,"trait":23,"subType":6},
{"localID":684,"teamName":"Joyriders","firstName":"Greg","lastName":"Vaughn","primaryPosition":7,"pitcherRole":null,"power":88,"contact":24,"speed":74,"fielding":59,"arm":51,"velocity":null,"junk":null,"accuracy":null,"age":30,"trait":15,"subType":6},
{"localID":688,"teamName":"Empire","firstName":"Billy","lastName":"Wagner","primaryPosition":1,"pitcherRole":4,"power":6,"contact":7,"speed":16,"fielding":40,"arm":null,"velocity":98,"junk":89,"accuracy":62,"age":23,"trait":22,"subType":14},
{"localID":689,"teamName":"Rakers","firstName":"Jered","lastName":"Weaver","primaryPosition":1,"pitcherRole":1,"power":3,"contact":6,"speed":25,"fielding":37,"arm":null,"velocity":35,"junk":73,"accuracy":77,"age":37,"trait":6,"subType":6},
{"localID":690,"teamName":"Rakers","firstName":"Brandon","lastName":"Webb","primaryPosition":1,"pitcherRole":1,"power":3,"contact":4,"speed":8,"fielding":73,"arm":null,"velocity":38,"junk":69,"accuracy":56,"age":34,"trait":33,"subType":25},
{"localID":695,"teamName":"Empire","firstName":"Jose","lastName":"Bautista","primaryPosition":9,"pitcherRole":null,"power":94,"contact":85,"speed":66,"fielding":75,"arm":99,"velocity":null,"junk":null,"accuracy":null,"age":29,"trait":0,"subType":0},
{"localID":695,"teamName":"Empire","firstName":"Jose","lastName":"Bautista","primaryPosition":9,"pitcherRole":null,"power":94,"contact":85,"speed":66,"fielding":75,"arm":99,"velocity":null,"junk":null,"accuracy":null,"age":29,"trait":32,"subType":6},
{"localID":698,"teamName":"Rakers","firstName":"Matt","lastName":"Williams","primaryPosition":5,"pitcherRole":null,"power":81,"contact":43,"speed":60,"fielding":93,"arm":90,"velocity":null,"junk":null,"accuracy":null,"age":30,"trait":12,"subType":11},
{"localID":699,"teamName":"Boomers","firstName":"Willie","lastName":"Wilson","primaryPosition":8,"pitcherRole":null,"power":21,"contact":66,"speed":99,"fielding":91,"arm":14,"velocity":null,"junk":null,"accuracy":null,"age":20,"trait":14,"subType":6},
{"localID":701,"teamName":"Spirit","firstName":"Kerry","lastName":"Wood","primaryPosition":1,"pitcherRole":1,"power":29,"contact":7,"speed":11,"fielding":39,"arm":null,"velocity":74,"junk":74,"accuracy":9,"age":19,"trait":null,"subType":null},
{"localID":704,"teamName":"Joyriders","firstName":"Robin","lastName":"Yount","primaryPosition":6,"pitcherRole":null,"power":49,"contact":79,"speed":86,"fielding":88,"arm":86,"velocity":null,"junk":null,"accuracy":null,"age":24,"trait":4,"subType":6},
{"localID":772,"teamName":"Rakers","firstName":"Mike","lastName":"Timlin","primaryPosition":1,"pitcherRole":3,"power":4,"contact":4,"speed":7,"fielding":74,"arm":null,"velocity":73,"junk":47,"accuracy":69,"age":21,"trait":23,"subType":6},
{"localID":772,"teamName":"Rakers","firstName":"Mike","lastName":"Timlin","primaryPosition":1,"pitcherRole":3,"power":4,"contact":4,"speed":7,"fielding":74,"arm":null,"velocity":73,"junk":47,"accuracy":69,"age":21,"trait":32,"subType":7},
{"localID":779,"teamName":"Rakers","firstName":"Lee","lastName":"Smith","primaryPosition":1,"pitcherRole":3,"power":1,"contact":1,"speed":0,"fielding":64,"arm":null,"velocity":94,"junk":72,"accuracy":69,"age":22,"trait":7,"subType":7},
{"localID":780,"teamName":"Spirit","firstName":"Jorge","lastName":"Posada","primaryPosition":2,"pitcherRole":null,"power":71,"contact":42,"speed":45,"fielding":25,"arm":74,"velocity":null,"junk":null,"accuracy":null,"age":32,"trait":17,"subType":6},
{"localID":782,"teamName":"Boomers","firstName":"Tom","lastName":"Burgmeier","primaryPosition":1,"pitcherRole":3,"power":7,"contact":2,"speed":5,"fielding":96,"arm":null,"velocity":54,"junk":47,"accuracy":81,"age":39,"trait":5,"subType":12},
{"localID":785,"teamName":"Empire","firstName":"Troy","lastName":"Glaus","primaryPosition":5,"pitcherRole":null,"power":88,"contact":29,"speed":60,"fielding":60,"arm":76,"velocity":null,"junk":null,"accuracy":null,"age":38,"trait":null,"subType":null},
{"localID":788,"teamName":"Originators","firstName":"Juan","lastName":"Marichal","primaryPosition":1,"pitcherRole":1,"power":9,"contact":2,"speed":2,"fielding":61,"arm":null,"velocity":73,"junk":42,"accuracy":95,"age":36,"trait":19,"subType":6},
{"localID":788,"teamName":"Originators","firstName":"Juan","lastName":"Marichal","primaryPosition":1,"pitcherRole":1,"power":9,"contact":2,"speed":2,"fielding":61,"arm":null,"velocity":73,"junk":42,"accuracy":95,"age":36,"trait":22,"subType":14},
{"localID":791,"teamName":"Empire","firstName":"Luis","lastName":"Gonzalez","primaryPosition":7,"pitcherRole":null,"power":66,"contact":73,"speed":69,"fielding":52,"arm":31,"velocity":null,"junk":null,"accuracy":null,"age":34,"trait":4,"subType":6},
{"localID":791,"teamName":"Empire","firstName":"Luis","lastName":"Gonzalez","primaryPosition":7,"pitcherRole":null,"power":66,"contact":73,"speed":69,"fielding":52,"arm":31,"velocity":null,"junk":null,"accuracy":null,"age":34,"trait":32,"subType":6},
{"localID":796,"teamName":"Rakers","firstName":"J.J.","lastName":"Putz","primaryPosition":1,"pitcherRole":3,"power":6,"contact":5,"speed":4,"fielding":66,"arm":null,"velocity":72,"junk":39,"accuracy":48,"age":34,"trait":5,"subType":12},
{"localID":804,"teamName":"Empire","firstName":"Cliff","lastName":"Lee","primaryPosition":1,"pitcherRole":1,"power":9,"contact":5,"speed":30,"fielding":19,"arm":null,"velocity":34,"junk":65,"accuracy":88,"age":32,"trait":18,"subType":6},
{"localID":808,"teamName":"Originators","firstName":"Eddie","lastName":"Mathews","primaryPosition":5,"pitcherRole":null,"power":92,"contact":70,"speed":27,"fielding":76,"arm":92,"velocity":null,"junk":null,"accuracy":null,"age":21,"trait":3,"subType":2},
{"localID":808,"teamName":"Originators","firstName":"Eddie","lastName":"Mathews","primaryPosition":5,"pitcherRole":null,"power":92,"contact":70,"speed":27,"fielding":76,"arm":92,"velocity":null,"junk":null,"accuracy":null,"age":21,"trait":17,"subType":7},
{"localID":812,"teamName":"Empire","firstName":"Grady","lastName":"Sizemore","primaryPosition":8,"pitcherRole":null,"power":66,"contact":40,"speed":77,"fielding":81,"arm":35,"velocity":null,"junk":null,"accuracy":null,"age":39,"trait":34,"subType":7},
{"localID":813,"teamName":"Joyriders","firstName":"Jeff","lastName":"Reardon","primaryPosition":1,"pitcherRole":3,"power":1,"contact":3,"speed":5,"fielding":13,"arm":null,"velocity":57,"junk":75,"accuracy":75,"age":39,"trait":null,"subType":null},
{"localID":819,"teamName":"Spirit","firstName":"Steve","lastName":"Finley","primaryPosition":8,"pitcherRole":null,"power":49,"contact":59,"speed":85,"fielding":83,"arm":46,"velocity":null,"junk":null,"accuracy":null,"age":33,"trait":0,"subType":0},
{"localID":820,"teamName":"Originators","firstName":"Reggie","lastName":"Smith","primaryPosition":8,"pitcherRole":null,"power":69,"contact":68,"speed":55,"fielding":55,"arm":68,"velocity":null,"junk":null,"accuracy":null,"age":35,"trait":0,"subType":0},
{"localID":820,"teamName":"Originators","firstName":"Reggie","lastName":"Smith","primaryPosition":8,"pitcherRole":null,"power":69,"contact":68,"speed":55,"fielding":55,"arm":68,"velocity":null,"junk":null,"accuracy":null,"age":35,"trait":3,"subType":2},
{"localID":823,"teamName":"Originators","firstName":"Willie","lastName":"Mays","primaryPosition":8,"pitcherRole":null,"power":97,"contact":91,"speed":45,"fielding":98,"arm":63,"velocity":null,"junk":null,"accuracy":null,"age":20,"trait":10,"subType":8},
{"localID":823,"teamName":"Originators","firstName":"Willie","lastName":"Mays","primaryPosition":8,"pitcherRole":null,"power":97,"contact":91,"speed":45,"fielding":98,"arm":63,"velocity":null,"junk":null,"accuracy":null,"age":20,"trait":29,"subType":6},
{"localID":830,"teamName":"Joyriders","firstName":"Mike","lastName":"Hampton","primaryPosition":1,"pitcherRole":1,"power":37,"contact":19,"speed":42,"fielding":72,"arm":null,"velocity":37,"junk":53,"accuracy":45,"age":23,"trait":7,"subType":7},
{"localID":831,"teamName":"Mammotanks","firstName":"David","lastName":"Ortiz","primaryPosition":3,"pitcherRole":null,"power":98,"contact":99,"speed":16,"fielding":25,"arm":42,"velocity":null,"junk":null,"accuracy":null,"age":28,"trait":3,"subType":3},
{"localID":831,"teamName":"Mammotanks","firstName":"David","lastName":"Ortiz","primaryPosition":3,"pitcherRole":null,"power":98,"contact":99,"speed":16,"fielding":25,"arm":42,"velocity":null,"junk":null,"accuracy":null,"age":28,"trait":32,"subType":6},
{"localID":834,"teamName":"Mammotanks","firstName":"Brian","lastName":"Wilson","primaryPosition":1,"pitcherRole":3,"power":6,"contact":4,"speed":0,"fielding":24,"arm":null,"velocity":74,"junk":20,"accuracy":19,"age":36,"trait":31,"subType":7},
{"localID":835,"teamName":"Mammotanks","firstName":"Bartolo","lastName":"Colon","primaryPosition":1,"pitcherRole":1,"power":90,"contact":0,"speed":21,"fielding":41,"arm":null,"velocity":54,"junk":64,"accuracy":83,"age":35,"trait":23,"subType":6},
{"localID":835,"teamName":"Mammotanks","firstName":"Bartolo","lastName":"Colon","primaryPosition":1,"pitcherRole":1,"power":90,"contact":0,"speed":21,"fielding":41,"arm":null,"velocity":54,"junk":64,"accuracy":83,"age":35,"trait":39,"subType":7},
{"localID":836,"teamName":"Spirit","firstName":"Devon","lastName":"White","primaryPosition":8,"pitcherRole":null,"power":51,"contact":39,"speed":95,"fielding":91,"arm":32,"velocity":null,"junk":null,"accuracy":null,"age":27,"trait":26,"subType":6},
{"localID":837,"teamName":"Originators","firstName":"Billy","lastName":"Williams","primaryPosition":7,"pitcherRole":null,"power":75,"contact":84,"speed":18,"fielding":41,"arm":86,"velocity":null,"junk":null,"accuracy":null,"age":29,"trait":14,"subType":7},
{"localID":839,"teamName":"Rakers","firstName":"Jose","lastName":"Valentin","primaryPosition":6,"pitcherRole":null,"power":70,"contact":23,"speed":80,"fielding":44,"arm":81,"velocity":null,"junk":null,"accuracy":null,"age":30,"trait":9,"subType":6},
{"localID":840,"teamName":"Rakers","firstName":"Harold","lastName":"Baines","primaryPosition":9,"pitcherRole":null,"power":62,"contact":71,"speed":51,"fielding":32,"arm":69,"velocity":null,"junk":null,"accuracy":null,"age":20,"trait":1,"subType":0},
{"localID":842,"teamName":"Rakers","firstName":"Mike","lastName":"Mussina","primaryPosition":1,"pitcherRole":1,"power":3,"contact":6,"speed":14,"fielding":87,"arm":null,"velocity":67,"junk":55,"accuracy":97,"age":37,"trait":20,"subType":6},
{"localID":842,"teamName":"Rakers","firstName":"Mike","lastName":"Mussina","primaryPosition":1,"pitcherRole":1,"power":3,"contact":6,"speed":14,"fielding":87,"arm":null,"velocity":67,"junk":55,"accuracy":97,"age":37,"trait":22,"subType":17},
{"localID":847,"teamName":"Rakers","firstName":"Mark","lastName":"Ellis","primaryPosition":4,"pitcherRole":null,"power":39,"contact":54,"speed":73,"fielding":86,"arm":59,"velocity":null,"junk":null,"accuracy":null,"age":20,"trait":null,"subType":null},
{"localID":849,"teamName":"Joyriders","firstName":"Sandy","lastName":"Alomar Jr.","primaryPosition":2,"pitcherRole":null,"power":37,"contact":63,"speed":45,"fielding":66,"arm":52,"velocity":null,"junk":null,"accuracy":null,"age":27,"trait":8,"subType":7},
{"localID":849,"teamName":"Joyriders","firstName":"Sandy","lastName":"Alomar Jr.","primaryPosition":2,"pitcherRole":null,"power":37,"contact":63,"speed":45,"fielding":66,"arm":52,"velocity":null,"junk":null,"accuracy":null,"age":27,"trait":33,"subType":25},
{"localID":850,"teamName":"Rakers","firstName":"Ellis","lastName":"Burks","primaryPosition":9,"pitcherRole":null,"power":77,"contact":62,"speed":79,"fielding":64,"arm":41,"velocity":null,"junk":null,"accuracy":null,"age":27,"trait":26,"subType":6},
{"localID":851,"teamName":"Empire","firstName":"Miguel","lastName":"Batista","primaryPosition":1,"pitcherRole":2,"power":7,"contact":3,"speed":21,"fielding":41,"arm":null,"velocity":48,"junk":50,"accuracy":12,"age":38,"trait":6,"subType":7},
{"localID":851,"teamName":"Empire","firstName":"Miguel","lastName":"Batista","primaryPosition":1,"pitcherRole":2,"power":7,"contact":3,"speed":21,"fielding":41,"arm":null,"velocity":48,"junk":50,"accuracy":12,"age":38,"trait":19,"subType":7},
{"localID":852,"teamName":"Joyriders","firstName":"Troy","lastName":"Percival","primaryPosition":1,"pitcherRole":4,"power":4,"contact":6,"speed":1,"fielding":28,"arm":null,"velocity":76,"junk":86,"accuracy":30,"age":23,"trait":18,"subType":7},
{"localID":852,"teamName":"Joyriders","firstName":"Troy","lastName":"Percival","primaryPosition":1,"pitcherRole":4,"power":4,"contact":6,"speed":1,"fielding":28,"arm":null,"velocity":76,"junk":86,"accuracy":30,"age":23,"trait":20,"subType":6},
{"localID":854,"teamName":"Mammotanks","firstName":"Joe","lastName":"Nathan","primaryPosition":1,"pitcherRole":4,"power":12,"contact":2,"speed":1,"fielding":43,"arm":null,"velocity":92,"junk":72,"accuracy":61,"age":33,"trait":20,"subType":6},
{"localID":854,"teamName":"Mammotanks","firstName":"Joe","lastName":"Nathan","primaryPosition":1,"pitcherRole":4,"power":12,"contact":2,"speed":1,"fielding":43,"arm":null,"velocity":92,"junk":72,"accuracy":61,"age":33,"trait":32,"subType":6},
{"localID":855,"teamName":"Spirit","firstName":"Bret","lastName":"Boone","primaryPosition":4,"pitcherRole":null,"power":62,"contact":45,"speed":66,"fielding":47,"arm":42,"velocity":null,"junk":null,"accuracy":null,"age":38,"trait":null,"subType":null},
{"localID":856,"teamName":"Empire","firstName":"Mark","lastName":"Buehrle","primaryPosition":1,"pitcherRole":1,"power":4,"contact":3,"speed":14,"fielding":91,"arm":null,"velocity":31,"junk":63,"accuracy":96,"age":38,"trait":22,"subType":19},
{"localID":856,"teamName":"Empire","firstName":"Mark","lastName":"Buehrle","primaryPosition":1,"pitcherRole":1,"power":4,"contact":3,"speed":14,"fielding":91,"arm":null,"velocity":31,"junk":63,"accuracy":96,"age":38,"trait":23,"subType":6},
{"localID":857,"teamName":"Rakers","firstName":"Cliff","lastName":"Floyd","primaryPosition":7,"pitcherRole":null,"power":63,"contact":44,"speed":68,"fielding":28,"arm":60,"velocity":null,"junk":null,"accuracy":null,"age":30,"trait":4,"subType":7},
{"localID":857,"teamName":"Rakers","firstName":"Cliff","lastName":"Floyd","primaryPosition":7,"pitcherRole":null,"power":63,"contact":44,"speed":68,"fielding":28,"arm":60,"velocity":null,"junk":null,"accuracy":null,"age":30,"trait":12,"subType":10},
{"localID":861,"teamName":"Thrillers","firstName":"Bert","lastName":"Blyleven","primaryPosition":1,"pitcherRole":1,"power":7,"contact":1,"speed":5,"fielding":82,"arm":null,"velocity":62,"junk":73,"accuracy":93,"age":36,"trait":5,"subType":13},
{"localID":861,"teamName":"Thrillers","firstName":"Bert","lastName":"Blyleven","primaryPosition":1,"pitcherRole":1,"power":7,"contact":1,"speed":5,"fielding":82,"arm":null,"velocity":62,"junk":73,"accuracy":93,"age":36,"trait":22,"subType":17},
{"localID":862,"teamName":"Originators","firstName":"Bob","lastName":"Locker","primaryPosition":1,"pitcherRole":3,"power":7,"contact":3,"speed":7,"fielding":69,"arm":null,"velocity":36,"junk":57,"accuracy":46,"age":23,"trait":6,"subType":6},
{"localID":862,"teamName":"Originators","firstName":"Bob","lastName":"Locker","primaryPosition":1,"pitcherRole":3,"power":7,"contact":3,"speed":7,"fielding":69,"arm":null,"velocity":36,"junk":57,"accuracy":46,"age":23,"trait":7,"subType":7},
{"localID":863,"teamName":"Mammotanks","firstName":"Johnny","lastName":"Damon","primaryPosition":8,"pitcherRole":null,"power":47,"contact":73,"speed":92,"fielding":72,"arm":40,"velocity":null,"junk":null,"accuracy":null,"age":21,"trait":29,"subType":6},
{"localID":863,"teamName":"Mammotanks","firstName":"Johnny","lastName":"Damon","primaryPosition":8,"pitcherRole":null,"power":47,"contact":73,"speed":92,"fielding":72,"arm":40,"velocity":null,"junk":null,"accuracy":null,"age":21,"trait":36,"subType":7},
{"localID":864,"teamName":"Mammotanks","firstName":"Mike","lastName":"Napoli","primaryPosition":2,"pitcherRole":null,"power":86,"contact":9,"speed":37,"fielding":74,"arm":72,"velocity":null,"junk":null,"accuracy":null,"age":33,"trait":4,"subType":7},
{"localID":865,"teamName":"Boomers","firstName":"George","lastName":"Foster","primaryPosition":7,"pitcherRole":null,"power":81,"contact":52,"speed":60,"fielding":68,"arm":67,"velocity":null,"junk":null,"accuracy":null,"age":29,"trait":8,"subType":7},
{"localID":866,"teamName":"Mammotanks","firstName":"Huston","lastName":"Street","primaryPosition":1,"pitcherRole":3,"power":2,"contact":0,"speed":2,"fielding":73,"arm":null,"velocity":53,"junk":32,"accuracy":79,"age":21,"trait":19,"subType":6},
{"localID":867,"teamName":"Mammotanks","firstName":"LaTroy","lastName":"Hawkins","primaryPosition":1,"pitcherRole":3,"power":3,"contact":0,"speed":2,"fielding":66,"arm":null,"velocity":75,"junk":48,"accuracy":68,"age":23,"trait":22,"subType":14},
{"localID":868,"teamName":"Thrillers","firstName":"Gary","lastName":"Gaetti","primaryPosition":5,"pitcherRole":null,"power":65,"contact":42,"speed":61,"fielding":93,"arm":84,"velocity":null,"junk":null,"accuracy":null,"age":19,"trait":3,"subType":4},
{"localID":869,"teamName":"Empire","firstName":"Keith","lastName":"Foulke","primaryPosition":1,"pitcherRole":3,"power":1,"contact":4,"speed":5,"fielding":55,"arm":null,"velocity":45,"junk":85,"accuracy":79,"age":27,"trait":22,"subType":19},
{"localID":870,"teamName":"Boomers","firstName":"Tom","lastName":"Seaver","primaryPosition":1,"pitcherRole":1,"power":17,"contact":1,"speed":36,"fielding":64,"arm":null,"velocity":89,"junk":63,"accuracy":75,"age":26,"trait":22,"subType":14},
{"localID":871,"teamName":"Empire","firstName":"Placido","lastName":"Polanco","primaryPosition":4,"pitcherRole":null,"power":30,"contact":90,"speed":66,"fielding":99,"arm":46,"velocity":null,"junk":null,"accuracy":null,"age":20,"trait":9,"subType":6},
{"localID":873,"teamName":"Boomers","firstName":"Alan","lastName":"Trammell","primaryPosition":6,"pitcherRole":null,"power":47,"contact":86,"speed":83,"fielding":79,"arm":91,"velocity":null,"junk":null,"accuracy":null,"age":37,"trait":3,"subType":3},
{"localID":873,"teamName":"Boomers","firstName":"Alan","lastName":"Trammell","primaryPosition":6,"pitcherRole":null,"power":47,"contact":86,"speed":83,"fielding":79,"arm":91,"velocity":null,"junk":null,"accuracy":null,"age":37,"trait":14,"subType":7},
{"localID":874,"teamName":"Spirit","firstName":"Craig","lastName":"Counsell","primaryPosition":4,"pitcherRole":null,"power":17,"contact":49,"speed":68,"fielding":90,"arm":71,"velocity":null,"junk":null,"accuracy":null,"age":31,"trait":1,"subType":0},
{"localID":875,"teamName":"Originators","firstName":"Bill","lastName":"Campbell","primaryPosition":1,"pitcherRole":3,"power":0,"contact":1,"speed":23,"fielding":67,"arm":null,"velocity":42,"junk":68,"accuracy":45,"age":29,"trait":22,"subType":20},
{"localID":878,"teamName":"Boomers","firstName":"Gene","lastName":"Tenace","primaryPosition":2,"pitcherRole":null,"power":74,"contact":39,"speed":53,"fielding":46,"arm":76,"velocity":null,"junk":null,"accuracy":null,"age":31,"trait":10,"subType":8},
{"localID":879,"teamName":"Empire","firstName":"Brad","lastName":"Ausmus","primaryPosition":2,"pitcherRole":null,"power":23,"contact":41,"speed":63,"fielding":97,"arm":78,"velocity":null,"junk":null,"accuracy":null,"age":28,"trait":26,"subType":7},
{"localID":880,"teamName":"Boomers","firstName":"Nolan","lastName":"Ryan","primaryPosition":1,"pitcherRole":1,"power":3,"contact":7,"speed":21,"fielding":19,"arm":null,"velocity":99,"junk":98,"accuracy":24,"age":36,"trait":7,"subType":6},
{"localID":880,"teamName":"Boomers","firstName":"Nolan","lastName":"Ryan","primaryPosition":1,"pitcherRole":1,"power":3,"contact":7,"speed":21,"fielding":19,"arm":null,"velocity":99,"junk":98,"accuracy":24,"age":36,"trait":22,"subType":14},
{"localID":881,"teamName":"Mammotanks","firstName":"Ryan","lastName":"Dempster","primaryPosition":1,"pitcherRole":2,"power":6,"contact":2,"speed":21,"fielding":59,"arm":null,"velocity":53,"junk":51,"accuracy":33,"age":23,"trait":null,"subType":null},
{"localID":883,"teamName":"Rakers","firstName":"Curtis","lastName":"Granderson","primaryPosition":8,"pitcherRole":null,"power":81,"contact":35,"speed":57,"fielding":85,"arm":55,"velocity":null,"junk":null,"accuracy":null,"age":38,"trait":26,"subType":6},
{"localID":884,"teamName":"Spirit","firstName":"Al","lastName":"Leiter","primaryPosition":1,"pitcherRole":2,"power":5,"contact":7,"speed":14,"fielding":44,"arm":null,"velocity":68,"junk":88,"accuracy":25,"age":24,"trait":34,"subType":6},
{"localID":884,"teamName":"Spirit","firstName":"Al","lastName":"Leiter","primaryPosition":1,"pitcherRole":2,"power":5,"contact":7,"speed":14,"fielding":44,"arm":null,"velocity":68,"junk":88,"accuracy":25,"age":24,"trait":39,"subType":7},
{"localID":885,"teamName":"Originators","firstName":"Johnny","lastName":"Bench","primaryPosition":2,"pitcherRole":null,"power":83,"contact":60,"speed":49,"fielding":74,"arm":96,"velocity":null,"junk":null,"accuracy":null,"age":24,"trait":2,"subType":6},
{"localID":886,"teamName":"Originators","firstName":"Don","lastName":"Sutton","primaryPosition":1,"pitcherRole":1,"power":7,"contact":7,"speed":10,"fielding":63,"arm":null,"velocity":54,"junk":65,"accuracy":87,"age":25,"trait":34,"subType":6},
{"localID":887,"teamName":"Originators","firstName":"Bucky","lastName":"Dent","primaryPosition":6,"pitcherRole":null,"power":16,"contact":62,"speed":43,"fielding":78,"arm":95,"velocity":null,"junk":null,"accuracy":null,"age":36,"trait":15,"subType":6},
{"localID":887,"teamName":"Originators","firstName":"Bucky","lastName":"Dent","primaryPosition":6,"pitcherRole":null,"power":16,"contact":62,"speed":43,"fielding":78,"arm":95,"velocity":null,"junk":null,"accuracy":null,"age":36,"trait":32,"subType":6},
{"localID":891,"teamName":"Originators","firstName":"Babe","lastName":"Ruth","primaryPosition":1,"pitcherRole":1,"power":99,"contact":96,"speed":20,"fielding":58,"arm":null,"velocity":67,"junk":86,"accuracy":58,"age":31,"trait":24,"subType":22},
{"localID":891,"teamName":"Originators","firstName":"Babe","lastName":"Ruth","primaryPosition":1,"pitcherRole":1,"power":99,"contact":96,"speed":20,"fielding":58,"arm":null,"velocity":67,"junk":86,"accuracy":58,"age":31,"trait":33,"subType":26},
{"localID":896,"teamName":"Originators","firstName":"Dave","lastName":"Parker","primaryPosition":9,"pitcherRole":null,"power":62,"contact":65,"speed":60,"fielding":27,"arm":77,"velocity":null,"junk":null,"accuracy":null,"age":22,"trait":32,"subType":7},
{"localID":897,"teamName":"Originators","firstName":"Chris","lastName":"Speier","primaryPosition":6,"pitcherRole":null,"power":33,"contact":52,"speed":54,"fielding":72,"arm":88,"velocity":null,"junk":null,"accuracy":null,"age":39,"trait":null,"subType":null}]
